flask_mab/__init__.py
flask_mab/bandits.py
flask_mab/debug_panels.py
flask_mab/mab.py
flask_mab/storage.py
flask_mab/templates/panels/mab-panel.html
flask_mab-3.0.4.dist-info/licenses/LICENSE
flask_mab-3.0.4.dist-info/METADATA
flask_mab-3.0.4.dist-info/WHEEL
flask_mab-3.0.4.dist-info/top_level.txt
flask_mab-3.0.4.dist-info/RECORD
