Metadata-Version: 2.4
Name: Flask-MAB
Version: 3.0.4
Summary: Multi-armed bandits for flask
Author-email: Mark Grey <mark.asperia@gmail.com>
Classifier: Environment :: Web Environment
Classifier: Intended Audience :: Developers
Classifier: License :: OSI Approved :: BSD License
Classifier: Operating System :: OS Independent
Classifier: Programming Language :: Python
Classifier: Topic :: Internet :: WWW/HTTP :: Dynamic Content
Classifier: Topic :: Software Development :: Libraries :: Python Modules
Requires-Python: >=3.9
License-File: LICENSE
Requires-Dist: Flask>=2.2.5
Requires-Dist: flask-debugtoolbar==0.16.0
Provides-Extra: dev
Requires-Dist: black==25.1.0; extra == "dev"
Requires-Dist: pytest==8.4.1; extra == "dev"
Requires-Dist: mock==5.2.0; extra == "dev"
Requires-Dist: tox==4.29.0; extra == "dev"
Provides-Extra: docs
Requires-Dist: sphinx-pyproject==0.3.0; extra == "docs"
Requires-Dist: sphinx==8.2.3; extra == "docs"
Requires-Dist: Pallets-Sphinx-Themes==2.3.0; extra == "docs"
Dynamic: license-file
